polymarket_ai_market_suggestor-0.2.0.dist-info/licenses/LICENSE
polysuggest/__init__.py
polysuggest/ai.py
polysuggest/analytics.py
polysuggest/cli.py
polysuggest/config.py
polysuggest/orchestrator.py
polysuggest/polymarket_client.py
polysuggest/py.typed
polysuggest/reporting.py
polysuggest/schemas.py
polysuggest/storage.py
polysuggest/trend_scanner.py
polymarket_ai_market_suggestor-0.2.0.dist-info/METADATA
polymarket_ai_market_suggestor-0.2.0.dist-info/WHEEL
polymarket_ai_market_suggestor-0.2.0.dist-info/entry_points.txt
polymarket_ai_market_suggestor-0.2.0.dist-info/top_level.txt
polymarket_ai_market_suggestor-0.2.0.dist-info/RECORD
