Metadata-Version: 2.4
Name: polymarket-ai-market-suggestor
Version: 0.2.0
Summary: AI agent that analyzes trends and suggests new Polymarket prediction markets in real time.
Author-email: Lorine93s <xsui46941@gmail.com>
License-Expression: Apache-2.0
Project-URL: Homepage, https://github.com/lorine93s/polymarket-ai-market-suggestor
Project-URL: Repository, https://github.com/lorine93s/polymarket-ai-market-suggestor
Project-URL: Issues, https://github.com/lorine93s/polymarket-ai-market-suggestor/issues
Keywords: polymarket,prediction-markets,ai,langchain,openai,trading,market-analysis
Classifier: Development Status :: 4 - Beta
Classifier: Environment :: Console
Classifier: Intended Audience :: Developers
Classifier: Intended Audience :: Financial and Insurance Industry
Classifier: Operating System :: OS Independent
Classifier: Programming Language :: Python :: 3
Classifier: Programming Language :: Python :: 3.11
Classifier: Programming Language :: Python :: 3.12
Classifier: Topic :: Office/Business :: Financial
Classifier: Topic :: Scientific/Engineering :: Artificial Intelligence
Classifier: Typing :: Typed
Requires-Python: >=3.11
License-File: LICENSE
Requires-Dist: typer==0.12.5
Requires-Dist: pydantic==2.9.2
Requires-Dist: requests==2.32.3
Requires-Dist: pandas==2.2.3
Requires-Dist: httpx==0.27.2
Requires-Dist: python-dotenv==1.0.1
Requires-Dist: loguru==0.7.2
Requires-Dist: langchain==0.3.4
Requires-Dist: langchain-openai==0.2.2
Requires-Dist: tiktoken==0.7.0
Requires-Dist: vaderSentiment==3.3.2
Requires-Dist: rapidfuzz==3.9.6
Requires-Dist: rich==13.9.2
Requires-Dist: click<8.1
Provides-Extra: chromadb
Requires-Dist: chromadb==0.5.5; extra == "chromadb"
Provides-Extra: dev
Requires-Dist: pytest; extra == "dev"
Requires-Dist: black; extra == "dev"
Requires-Dist: ruff; extra == "dev"
Dynamic: license-file
